diffx/__init__.py
diffx/base.py
diffx/differ.py
diffx/hash.py
diffx/xpath.py
diffx/svg/__init__.py
diffx/svg/coloured_text.py
diffx/svg/coloured_without_text.py
diffx/svg/compact.py
diffx/svg/render_text.py
XmlXdiff-1.0.0.dist-info/METADATA
XmlXdiff-1.0.0.dist-info/WHEEL
XmlXdiff-1.0.0.dist-info/top_level.txt
XmlXdiff-1.0.0.dist-info/zip-safe
XmlXdiff-1.0.0.dist-info/RECORD
