Metadata-Version: 2.1
Name: XmlXdiff
Version: 1.0.0
Summary: Compare xml files with svg output.
Home-page: https://github.com/mmoosstt/XmlXdiff
Author: mmoosstt
Author-email: diponaut@gmx.de
License: LGPL
Platform: UNKNOWN
Requires-Dist: PySide2
Requires-Dist: lxml
Requires-Dist: svgwrite
